Workbook

Sheet Assumptions
A1: Investice | B1: 1000000
A2: Tržby rok 1 | B2: 5000000
A3: Růst tržeb % | B3: 0.05
A4: Marže EBITDA % | B4: 0.2
A5: Diskont % | B5: 0.08
A6: Dluh | B6: 600000
A7: Úrok % | B7: 0.06
A8: Doba splácení (roky) | B8: 3
A9: CAPEX ročně | B9: 100000
A10: Daň % | B10: 0.19
A11: Working Capital % | B11: 0.05
A12: Dlouhodobý růst g | B12: 0.02

Sheet Model
A4: Rok 1 | B4: Rok 2 | C4: Rok 3
A5: Tržby | B5: =Assumptions!B2 -> 5000000 | C5: =B5*(1+Assumptions!B3) -> 5250000 | D5: =C5*(1+Assumptions!B3) -> 5512500
A6: EBITDA | B6: =B5*Assumptions!B4 -> 1000000 | C6: =C5*Assumptions!B4 -> 1050000 | D6: =D5*Assumptions!B4 -> 1102500
A7: FCF | B7: =B6-Assumptions!B9 -> 900000 | C7: =C6-Assumptions!B9 -> 950000 | D7: =D6-Assumptions!B9 -> 1002500

Sheet Debt_Model
A3: Počáteční dluh | B3: =Assumptions!B6 -> 600000 | C3: =B6 -> 400000 | D3: =C6 -> 200000 | E3: =D6 -> 0
A4: Úrok | B4: =B3*Assumptions!B7 -> 36000 | C4: =C3*Assumptions!B7 -> 24000 | D4: =D3*Assumptions!B7 -> 12000 | E4: =E3*Assumptions!B7 -> 0
A5: Splátka | B5: =Assumptions!B6/Assumptions!B8 -> 200000 | C5: =B5 -> 200000 | D5: =C5 -> 200000
A6: Zůstatek dluhu | B6: =B3-B5 -> 400000 | C6: =C3-C5 -> 200000 | D6: =D3-D5 -> 0
